{
  "^GSPC": {
    "name": "S&P 500",
    "price": 6946.1298828125,
    "change": 56.05988281250029,
    "changePercent": 0.8136329937504306,
    "updatedAt": "2026-02-26T03:33:36.635665"
  },
  "2559.T": {
    "name": "全世界 (オールカントリー)",
    "price": 27165.0,
    "change": 230.0,
    "changePercent": 0.8539075552255428,
    "updatedAt": "2026-02-26T03:33:36.860387"
  },
  "^TPX": {
    "name": "TOPIX",
    "price": 4083.0,
    "change": 41.0,
    "changePercent": 1.0143493320138546,
    "updatedAt": "2026-02-26T03:33:37.108618"
  }
}