{
  "^GSPC": {
    "name": "S&P 500",
    "price": 6908.85986328125,
    "change": -37.27013671875011,
    "changePercent": -0.5365597349711293,
    "updatedAt": "2026-02-27T03:30:29.998406"
  },
  "2559.T": {
    "name": "全世界 (オールカントリー)",
    "price": 27015.0,
    "change": -145.0,
    "changePercent": -0.5338733431516937,
    "updatedAt": "2026-02-27T03:30:30.379679"
  },
  "^TPX": {
    "name": "TOPIX",
    "price": 4108.0,
    "change": 32.0,
    "changePercent": 0.7850834151128557,
    "updatedAt": "2026-02-27T03:30:30.672302"
  }
}